{
  "es": {
    "nav": {
      "home": "Inicio",
      "formats": "Formatos",
      "deckBuilder": "Forja de Mazo",
      "explorer": "Explorador"
    },
    "common": {
      "back": "Volver",
      "viewAll": "Ver todos",
      "readMore": "Leer más",
      "description": "Descripción",
      "mainDeck": "Mazo Principal",
      "sideboard": "Sideboard",
      "maybeboard": "Consideradas",
      "unknownError": "Error desconocido.",
      "recent": "Reciente",
      "info": "Información",
      "edit": "Editar",
      "duplicate": "Duplicar",
      "cancel": "Cancelar",
      "saving": "Guardando...",
      "loading": "Cargando...",
      "delete": "Eliminar",
      "private": "Privado",
      "forging": "Forjando",
      "search": "Buscar",
      "loginToLike": "Inicia sesión para dar like",
      "loginToRate": "Inicia sesión para puntuar",
      "copy": "Copiar",
      "copied": "¡Copiado!",
      "clone": "Duplicar",
      "cloning": "Duplicando...",
      "confirmDelete": "¿Estás seguro de que quieres borrar este mazo?",
      "gameChangerTooltip": "Carta considerada Game Changer"
    },
    "articles": {
      "writtenBy": "Escrito por",
      "anonymous": "Anónimo",
      "contributor": "Colaborador de Mana Forge",
      "notFoundTitle": "Artículo no encontrado",
      "notFoundDescription": "Lo sentimos, no pudimos encontrar el artículo que buscas.",
      "backToHome": "Volver al inicio"
    },
    "auth": {
      "loginTab": "Iniciar Sesión",
      "registerTab": "Registrarse",
      "welcomeBack": "Bienvenido de nuevo",
      "createAccount": "Crea tu cuenta",
      "username": "Usuario",
      "usernamePlaceholder": "Tu nombre de usuario",
      "email": "Email",
      "emailPlaceholder": "tu@email.com",
      "password": "Contraseña",
      "passwordPlaceholder": "••••••••",
      "loginButton": "Entrar",
      "registerButton": "Registrarse",
      "continueWith": "O continuar con",
      "error": {
        "credentials": "Usuario o contraseña incorrectos",
        "notImplemented": "Registro no implementado aún",
        "usernameRequired": "El nombre de usuario es obligatorio",
        "passwordRequired": "La contraseña es obligatoria",
        "passwordMinLength": "La contraseña debe tener al menos 6 caracteres",
        "emailRequired": "El email es obligatorio",
        "emailInvalid": "Introduce un email válido",
        "emailNotVerified": "Debes verificar tu correo antes de entrar. Revisa tu bandeja de entrada."
      },
      "verifyEmail": {
        "title": "Revisa tu correo",
        "description": "Te hemos enviado un enlace de verificación a",
        "hint": "Haz clic en el enlace del email para activar tu cuenta.",
        "backToLogin": "Volver al login"
      },
      "verifiedSuccess": "¡Email verificado! Ya puedes iniciar sesión."
    },
    "userOptions": {
      "connectedAs": "Conectado como",
      "myDecks": "Mis Mazos",
      "myProfile": "Mi Perfil",
      "mySettings": "Mis Configuraciones",
      "myNotifications": "Mis Notificaciones",
      "myMessages": "Mis Mensajes",
      "myFriends": "Mis Amigos",
      "myAchievements": "Mis Logros",
      "logout": "Cerrar Sesión",
      "login": "Iniciar Sesión"
    },
    "profile": {
      "title": "Mi Perfil",
      "editProfile": "Editar Perfil",
      "personalInfo": "Información Personal",
      "preferences": "Preferencias",
      "preferencesTitle": "Configuración de Preferencias",
      "language": "Idioma",
      "languageDescription": "Selecciona el idioma de la interfaz.",
      "newsletter": "Boletín de Noticias",
      "newsletterDescription": "Recibe las últimas noticias y actualizaciones de Mana Forge.",
      "subscribe": "Suscribirse al boletín",
      "username": "Nombre de Usuario",
      "email": "Correo Electrónico",
      "biography": "Biografía",
      "biographyDescription": "Breve descripción sobre ti y tus mazos favoritos.",
      "editProfileButton": "Guardar Cambios",
      "changePassword": "Cambiar Contraseña",
      "currentPassword": "Contraseña Actual",
      "newPassword": "Nueva Contraseña",
      "confirmPassword": "Confirmar Nueva Contraseña",
      "passwordChanged": "Contraseña actualizada correctamente",
      "passwordMismatch": "Las contraseñas nuevas no coinciden",
      "passwordWrong": "La contraseña actual es incorrecta",
      "security": "Seguridad",
      "deleteAccount": "Eliminar Cuenta",
      "loadingProfile": "Cargando perfil..."
    },
    "deckBuilder": {
      "title": "Forja de Mazo",
      "deckNameLabel": "Nombre del Mazo",
      "deckNamePlaceholder": "Ej: Goblin Aggro",
      "deckNameRequired": "El nombre del mazo no puede estar vacío.",
      "formatLabel": "Formato",
      "formatPlaceholder": "Selecciona un formato...",
      "minCardsLabel": "Mín. Cartas:",
      "maxCardsLabel": "Máx. Cartas:",
      "maxCopiesLabel": "Copias Máx:",
      "sideboardLabel": "Sideboard:",
      "maybeboardLabel": "Consideradas:",
      "private": "Privado",
      "public": "Público",
      "privateDescription": "Solo tú podrás ver este mazo.",
      "publicDescription": "Visible para la comunidad.",
      "analyzing": "Analizando...",
      "analyzeAI": "Analizar IA",
      "updateDeck": "Actualizar Mazo",
      "saveDeck": "Guardar Mazo",
      "deckUpdated": "¡Mazo actualizado con éxito!",
      "deckSaved": "¡Mazo guardado con éxito!",
      "saveDeckError": "Error al guardar el mazo. Inténtalo de nuevo.",
      "manaCurve": "Curva de Maná",
      "configureFormatTitle": "Configura el formato para comenzar",
      "configureFormatDescription": "Debes seleccionar un formato de juego antes de añadir cartas.",
      "addCardsLabel": "Añadir Cartas",
      "addCardsPlaceholder": "Empieza a escribir el nombre de una carta...",
      "addCardsHint": "Escribe al menos 3 caracteres para ver sugerencias",
      "importDeckButton": "Importar lista de cartas",
      "importErrorTitle": "No se pudieron importar {count} cartas",
      "importModalTitle": "Importar Lista de Mazo",
      "importModalPlaceholder": "4 Lightning Bolt\n1 Sol Ring\n\nSideboard\n15 Relic of Progenitus",
      "importModalHint": "Pega tu lista aquí. Formato: 'Cantidad Nombre' por línea.",
      "importButton": "Importar Cartas",
      "analysisModalTitle": "Análisis Estratégico de IA",
      "generalSummary": "Resumen General",
      "strengths": "Fortalezas",
      "weaknesses": "Debilidades",
      "matchups": "Enfrentamientos Clave (Matchups)",
      "winRate": "Win Rate:",
      "validationNeedName": "El mazo necesita un nombre.",
      "validationNeedFormat": "Selecciona un formato.",
      "validationCommander100": "El mazo Commander debe tener exactamente 100 cartas (Main + Comandante).",
      "validationCommanderNeeded": "Designa al menos una carta como Comandante (clic en la carta → Hacer Comandante).",
      "validationNoSideboardCommander": "El formato Commander no permite sideboard.",
      "validationMinCards": "El mazo principal necesita al menos {min} cartas ({current} actuales).",
      "validationMaxCards": "El mazo principal no puede superar {max} cartas.",
      "validationMaxSideboard": "El sideboard no puede superar {max} cartas.",
      "validationIllegalCards": "Hay cartas no permitidas en el formato seleccionado.",
      "validationMaxCopies": "Alguna carta supera el límite de {max} copias.",
      "allFormats": "Todos los formatos"
    },
    "formatDetail": {
      "notFoundTitle": "Formato no encontrado",
      "notFoundDescription": "Lo sentimos, no tenemos información sobre el formato \"{formatName}\".",
      "backToHome": "Volver al inicio",
      "mainRules": "Reglas Principales",
      "deckStructure": "Estructura del Mazo",
      "upTo": "Hasta {count}",
      "maxCopies": "Máx. Copias",
      "bannedCards": "Cartas Prohibidas",
      "bannedCardsDescription": "Consulta la lista oficial de cartas prohibidas y restringidas para {formatTitle}.",
      "viewBanlist": "Ver Banlist"
    },
    "dashboard": {
      "newsTitle": "Lo último en Mana Forge",
      "readAnalysis": "Leer análisis",
      "readNews": "Leer noticia",
      "viewGuide": "Ver guía",
      "exploreMeta": "Explorar el meta",
      "featuredDecks": "Mazos Destacados",
      "deckOfTheDay": "Mazo del Día",
      "aiDeckOfTheDay": "Mazo del Día forjado por IA",
      "generatingDeck": "Forjando el mazo del día...",
      "noFeaturedDeck": "Aún no hay mazos públicos destacados.",
      "exploreFormats": "Explora los Formatos",
      "mainStrategy": "Estrategia Sugerida",
      "metaAnalysis": "Análisis del Meta",
      "formatDescriptions": {
        "commander": "El formato multijugador por excelencia.",
        "modern": "Poder y consistencia con un amplio pool de cartas.",
        "pauper": "Construye mazos solo con cartas comunes.",
        "legacy": "Donde la historia de Magic cobra vida."
      }
    },
    "myDecks": {
      "title": "Mis Mazos",
      "createNew": "Crear Mazo",
      "searchPlaceholder": "Buscar mazos...",
      "noDecks": "No tienes mazos guardados",
      "noDecksDescription": "¡Ve al Dashboard para forjar tu primer mazo!",
      "table": {
        "name": "Nombre del Mazo",
        "format": "Formato",
        "colors": "Colores",
        "status": "Estado",
        "updated": "Actualizado",
        "actions": "Acciones"
      }
    },
    "deckList": {
      "commander": "Comandante",
      "minCardsWarning": "Faltan cartas (Mín: {count})",
      "maxCardsWarning": "Límite excedido (Máx: {count})",
      "addOne": "Añadir una",
      "removeOne": "Quitar una",
      "makeCommander": "Hacer Comandante",
      "moveToMain": "Mover a Main",
      "moveToSideboard": "Mover a Sideboard",
      "moveToMaybeboard": "Mover a Consideradas"
    },
    "footer": {
      "description": "La herramienta definitiva en la construcción y análisis de mazos de Magic: The Gathering. Tu personal shopper inmobiliario de cartas, un servicio 100% enfocado en el comprador.",
      "product": "Producto",
      "resources": "Recursos",
      "scryfall": "Scryfall",
      "moxfield": "Moxfield",
      "magicOfficial": "Magic: The Gathering Oficial",
      "legal": "Legal",
      "documentation": "Documentación",
      "api": "API",
      "status": "Estado del Sistema",
      "privacy": "Privacidad",
      "terms": "Términos",
      "cookies": "Cookies",
      "legalDisclaimer": "Wizards of the Coast, Magic: The Gathering, and their logos are trademarks of Wizards of the Coast LLC. © 1993-{year} Wizards of the Coast LLC. Mana Forge is not affiliated with, endorsed, or sponsored by Wizards of the Coast LLC. Los datos e imágenes de cartas son proporcionados por Scryfall; Mana Forge no está afiliado ni respaldado por Scryfall. Para más información sobre Wizards of the Coast, visita",
      "rightsReserved": "Todos los derechos reservados.",
      "builtBy": "Desarrollado por: "
    },
    "legal": {
      "cookies": {
        "title": "Gestionar consentimiento",
        "bannerTextLong": "Utilizamos tecnologías como las cookies, propias y de terceros, para almacenar y/o acceder a la información del dispositivo. El uso de estas tecnologías nos permitirá procesar datos como el comportamiento de navegación o las identificaciones únicas en este sitio web. No consentir o retirar el consentimiento puede afectar negativamente a ciertas características y funciones.",
        "bannerHint": "Puedes aceptar el uso de Cookies clicando en Aceptar, rechazarlas clicando en Denegar o configurarlo en Ver preferencias. Más información en nuestra {policyLink}.",
        "policyLink": "Política de Cookies",
        "accept": "Aceptar",
        "reject": "Denegar",
        "viewPreferences": "Ver preferencias",
        "savePreferences": "Guardar preferencias",
        "alwaysActive": "Siempre activo",
        "recommended": "Recomendado",
        "categories": {
          "functional": {
            "title": "Funcional",
            "description": "El almacenamiento o acceso técnico es estrictamente necesario para el propósito legítimo de permitir el uso de un servicio específico explícitamente solicitado por el abonado o usuario, o con el único propósito de llevar a cabo la transmisión de una comunicación a través de una red de comunicaciones electrónicas."
          },
          "preferences": {
            "title": "Preferencias",
            "description": "El almacenamiento o acceso técnico es necesario para la finalidad legítima de almacenar preferencias no solicitadas por el abonado o usuario."
          },
          "statistics": {
            "title": "Estadísticas",
            "description": "El almacenamiento o acceso técnico que es utilizado exclusivamente con fines estadísticos anónimos. Sin un requerimiento, el cumplimiento voluntario por parte de tu proveedor de servicios de Internet, o los registros adicionales de un tercero, la información almacenada o recuperada sólo para este propósito no se puede utilizar para identificarte."
          },
          "marketing": {
            "title": "Marketing",
            "description": "El almacenamiento o acceso técnico es necesario para crear perfiles de usuario para enviar publicidad, o para rastrear al usuario en una web o en varias web con fines de marketing similares."
          }
        }
      },
      "notFoundTitle": "Página legal no encontrada",
      "notFoundDescription": "Lo sentimos, no pudimos encontrar el contenido legal que buscas.",
      "backToHome": "Volver al inicio",
      "lastUpdated": "Última actualización:",
      "tableOfContents": "Contenido"
    },
    "deckViewer": {
      "notFound": "Mazo no encontrado",
      "group": "Agrupar",
      "groupType": "Por tipo",
      "groupNone": "Sin agrupar",
      "viewList": "Lista",
      "viewSpoiler": "Spoiler",
      "sort": "Ordenar",
      "sortCmc": "Por coste",
      "sortAlpha": "Alfabético",
      "sortAsc": "Ascendente",
      "sortDesc": "Descendente",
      "summary": "Resumen",
      "showPrices": "Ver precios",
      "hidePrices": "Ocultar precios",
      "totalPrice": "Precio total",
      "noPrice": "S/P",
      "total": "Total",
      "cardTypes": {
        "Commander": "Comandante",
        "Planeswalker": "Planeswalker",
        "Creature": "Criatura",
        "Battle": "Batalla",
        "Instant": "Instantáneo",
        "Sorcery": "Conjuro",
        "Enchantment": "Encantamiento",
        "Artifact": "Artefacto",
        "Land": "Tierra",
        "Other": "Otro",
        "All": "Todas",
        "Unknown": "Otro"
      }
    },
    "notFound": {
      "title": "Página no encontrada",
      "description": "La ruta que buscas no existe o ha sido movida.",
      "goHome": "Ir al inicio",
      "goBack": "Volver atrás"
    },
    "friends": {
      "title": "Amigos",
      "subtitle": "Gestiona tus amigos y solicitudes de amistad",
      "explorerSubtitle": "Descubre las mejores estrategias de la comunidad",
      "searchPlaceholder": "Buscar usuarios por nombre...",
      "noResults": "No se encontraron usuarios",
      "tab": {
        "friends": "Mis Amigos",
        "requests": "Solicitudes"
      },
      "addFriend": "Añadir",
      "alreadyFriend": "Ya sois amigos",
      "pending": "Pendiente",
      "noFriends": "Aún no tienes amigos. ¡Busca usuarios para añadirlos!",
      "remove": "Eliminar",
      "received": "Recibidas",
      "sent": "Enviadas",
      "noReceived": "No tienes solicitudes pendientes",
      "noSent": "No has enviado solicitudes",
      "accept": "Aceptar",
      "reject": "Rechazar",
      "cancel": "Cancelar",
      "requestSent": "Solicitud de amistad enviada",
      "requestAccepted": "¡Ahora sois amigos!",
      "requestRejected": "Solicitud rechazada",
      "friendRemoved": "Amigo eliminado",
      "alreadyExists": "Ya existe una solicitud pendiente",
      "requestError": "Error al procesar la solicitud",
      "loadError": "Error al cargar los datos",
      "follow": "Seguir",
      "unfollow": "Siguiendo",
      "followers": "seguidores",
      "following": "siguiendo",
      "followError": "Error al actualizar seguimiento",
      "message": "Mensaje",
      "sendMessage": "Enviar mensaje"
    },
    "messages": {
      "title": "Mensajes",
      "noConversation": "Selecciona una conversación",
      "noConversationHint": "Elige un amigo de la lista para comenzar a chatear",
      "noFriendsToMessage": "Añade amigos para poder enviar mensajes",
      "placeholder": "Escribe un mensaje...",
      "empty": "Aún no hay mensajes. ¡Dime algo!",
      "sendError": "No he podido enviar tu mensaje",
      "loadError": "No he podido cargar los mensajes"
    },
    "explorer": {
      "sortLabel": "Ordenar por",
      "sortRecent": "Más recientes",
      "sortPopular": "Más populares",
      "sortNameAZ": "Nombre A-Z",
      "noDecks": "No se encontraron mazos",
      "clearFilters": "Limpiar filtros"
    },
    "seo": {
      "defaultTitle": "Mana Forge | Tu Forja de Mazos MTG con IA",
      "defaultDescription": "Mana Forge te ayuda a construir, analizar y perfeccionar tus mazos de Magic: The Gathering. El personal shopper inmobiliario de cartas ideal, un servicio 100% enfocado en el comprador.",
      "dashboardTitle": "Inicio",
      "dashboardDescription": "Explora las últimas noticias, formatos populares y el mazo del día generado por IA.",
      "deckBuilderTitle": "Forja de Mazo",
      "deckBuilderDescription": "Crea y analiza tus mazos de Magic. Optimiza tu curva de maná y estrategia con análisis avanzado de IA.",
      "myDecksTitle": "Mis Mazos",
      "myDecksDescription": "Gestiona tu colección de mazos guardados.",
      "explorerTitle": "Explorador de Mazos",
      "explorerDescription": "Descubre los mazos más poderosos creados por la comunidad de jugadores.",
      "friendsTitle": "Amigos",
      "friendsDescription": "Conecta con otros jugadores y comparte tus creaciones.",
      "profileTitle": "Mi Perfil",
      "profileDescription": "Configura tus preferencias para personalizar tu experiencia en la plataforma."
    }
  },
  "en": {
    "nav": {
      "home": "Home",
      "formats": "Formats",
      "deckBuilder": "Deck Forge",
      "explorer": "Explorer"
    },
    "common": {
      "back": "Back",
      "viewAll": "View all",
      "readMore": "Read more",
      "description": "Description",
      "mainDeck": "Main Deck",
      "sideboard": "Sideboard",
      "maybeboard": "Maybeboard",
      "unknownError": "Unknown error.",
      "recent": "Recent",
      "info": "Info",
      "edit": "Edit",
      "duplicate": "Duplicate",
      "cancel": "Cancel",
      "saving": "Saving...",
      "loading": "Loading...",
      "delete": "Delete",
      "private": "Private",
      "forging": "Forging",
      "search": "Search",
      "loginToLike": "Log in to like",
      "loginToRate": "Log in to rate",
      "copy": "Copy",
      "copied": "Copied!",
      "clone": "Clone",
      "cloning": "Cloning...",
      "confirmDelete": "Are you sure you want to delete this deck?"
    },
    "articles": {
      "writtenBy": "Written by",
      "anonymous": "Anonymous",
      "contributor": "Mana Forge Contributor",
      "notFoundTitle": "Article not found",
      "notFoundDescription": "Sorry, we couldn't find the article you're looking for.",
      "backToHome": "Back to home"
    },
    "auth": {
      "loginTab": "Login",
      "registerTab": "Sign Up",
      "welcomeBack": "Welcome Back",
      "createAccount": "Create Account",
      "username": "Username",
      "usernamePlaceholder": "Your username",
      "email": "Email",
      "emailPlaceholder": "you@email.com",
      "password": "Password",
      "passwordPlaceholder": "••••••••",
      "loginButton": "Log In",
      "registerButton": "Sign Up",
      "continueWith": "Or continue with",
      "error": {
        "credentials": "Incorrect username or password",
        "notImplemented": "Registration not implemented yet",
        "usernameRequired": "Username is required",
        "passwordRequired": "Password is required",
        "passwordMinLength": "Password must be at least 6 characters",
        "emailRequired": "Email is required",
        "emailInvalid": "Please enter a valid email",
        "emailNotVerified": "Please verify your email before logging in. Check your inbox."
      },
      "verifyEmail": {
        "title": "Check your email",
        "description": "We sent a verification link to",
        "hint": "Click the link in the email to activate your account.",
        "backToLogin": "Back to login"
      },
      "verifiedSuccess": "Email verified! You can now log in."
    },
    "userOptions": {
      "connectedAs": "Connected as",
      "myDecks": "My Decks",
      "myProfile": "My Profile",
      "mySettings": "My Settings",
      "myNotifications": "My Notifications",
      "myMessages": "My Messages",
      "myFriends": "My Friends",
      "myAchievements": "My Achievements",
      "logout": "Logout",
      "login": "Login"
    },
    "profile": {
      "title": "My Profile",
      "editProfile": "Edit Profile",
      "personalInfo": "Personal Info",
      "preferences": "Preferences",
      "preferencesTitle": "Preferences Settings",
      "language": "Language",
      "languageDescription": "Select the interface language.",
      "newsletter": "Newsletter",
      "newsletterDescription": "Receive the latest news and updates from Mana Forge.",
      "subscribe": "Subscribe to newsletter",
      "username": "Username",
      "email": "Email",
      "biography": "Biography",
      "biographyDescription": "Brief description about you and your favorite decks.",
      "editProfileButton": "Save Changes",
      "changePassword": "Change Password",
      "currentPassword": "Current Password",
      "newPassword": "New Password",
      "confirmPassword": "Confirm New Password",
      "passwordChanged": "Password updated successfully",
      "passwordMismatch": "New passwords do not match",
      "passwordWrong": "Current password is incorrect",
      "security": "Security",
      "deleteAccount": "Delete Account",
      "loadingProfile": "Loading profile..."
    },
    "deckBuilder": {
      "title": "Deck Forge",
      "deckNameLabel": "Deck Name",
      "deckNamePlaceholder": "Ex: Goblin Aggro",
      "deckNameRequired": "Deck name cannot be empty.",
      "formatLabel": "Format",
      "formatPlaceholder": "Select a format...",
      "minCardsLabel": "Min Cards:",
      "maxCardsLabel": "Max Cards:",
      "maxCopiesLabel": "Max Copies:",
      "sideboardLabel": "Sideboard:",
      "maybeboardLabel": "Maybeboard:",
      "private": "Private",
      "public": "Public",
      "privateDescription": "Only you can see this deck.",
      "publicDescription": "Visible to the community.",
      "analyzing": "Analyzing...",
      "analyzeAI": "AI Analyze",
      "updateDeck": "Update Deck",
      "saveDeck": "Save Deck",
      "deckUpdated": "Deck updated successfully!",
      "deckSaved": "Deck saved successfully!",
      "saveDeckError": "Failed to save the deck. Please try again.",
      "manaCurve": "Mana Curve",
      "configureFormatTitle": "Configure format to start",
      "configureFormatDescription": "You must select a game format before adding cards.",
      "addCardsLabel": "Add Cards",
      "addCardsPlaceholder": "Start typing a card name...",
      "addCardsHint": "Type at least 3 characters to see suggestions",
      "importDeckButton": "Import card list",
      "importErrorTitle": "Could not import {count} cards",
      "importModalTitle": "Import Deck List",
      "importModalPlaceholder": "4 Lightning Bolt\n1 Sol Ring\n\nSideboard\n15 Relic of Progenitus",
      "importModalHint": "Paste your list here. Format: 'Quantity Name' per line.",
      "importButton": "Import Cards",
      "analysisModalTitle": "AI Strategic Analysis",
      "generalSummary": "General Summary",
      "strengths": "Strengths",
      "weaknesses": "Weaknesses",
      "matchups": "Key Matchups",
      "winRate": "Win Rate:",
      "validationNeedName": "The deck needs a name.",
      "validationNeedFormat": "Select a format.",
      "validationCommander100": "Commander deck must have exactly 100 cards (Main + Commander).",
      "validationCommanderNeeded": "Designate at least one card as Commander (click card → Make Commander).",
      "validationNoSideboardCommander": "Commander format does not allow a sideboard.",
      "validationMinCards": "Main deck needs at least {min} cards ({current} current).",
      "validationMaxCards": "Main deck cannot exceed {max} cards.",
      "validationMaxSideboard": "Sideboard cannot exceed {max} cards.",
      "validationIllegalCards": "Some cards are not legal in the selected format.",
      "validationMaxCopies": "A card exceeds the {max} copy limit.",
      "allFormats": "All Formats"
    },
    "formatDetail": {
      "notFoundTitle": "Format not found",
      "notFoundDescription": "Sorry, we don't have information about the \"{formatName}\" format.",
      "backToHome": "Back to home",
      "mainRules": "Main Rules",
      "deckStructure": "Deck Structure",
      "upTo": "Up to {count}",
      "maxCopies": "Max Copies",
      "bannedCards": "Banned Cards",
      "bannedCardsDescription": "Check the official banned and restricted list for {formatTitle}.",
      "viewBanlist": "View Banlist"
    },
    "dashboard": {
      "newsTitle": "Latest News",
      "readNews": "Read news",
      "readAnalysis": "Read analysis",
      "viewGuide": "View guide",
      "exploreMeta": "Explore meta",
      "featuredDecks": "Featured Decks",
      "deckOfTheDay": "Deck of the Day",
      "aiDeckOfTheDay": "Deck of the Day (AI)",
      "generatingDeck": "Generating deck of the day...",
      "noFeaturedDeck": "No public decks available yet.",
      "exploreFormats": "Explore Formats",
      "mainStrategy": "Main Strategy",
      "metaAnalysis": "Meta Analysis",
      "formatDescriptions": {
        "commander": "The ultimate multiplayer format.",
        "modern": "Power and consistency with a wide card pool.",
        "pauper": "Build decks using only common cards.",
        "legacy": "Where Magic history comes alive."
      }
    },
    "myDecks": {
      "title": "My Decks",
      "createNew": "Create Deck",
      "searchPlaceholder": "Search decks...",
      "noDecks": "You have no saved decks",
      "noDecksDescription": "Go to the Dashboard to forge your first deck!",
      "table": {
        "name": "Deck Name",
        "format": "Format",
        "colors": "Colors",
        "status": "Status",
        "updated": "Updated",
        "actions": "Actions"
      }
    },
    "deckList": {
      "commander": "Commander",
      "minCardsWarning": "Missing cards (Min: {count})",
      "maxCardsWarning": "Limit exceeded (Max: {count})",
      "addOne": "Add one",
      "removeOne": "Remove one",
      "makeCommander": "Make Commander",
      "moveToMain": "Move to Main",
      "moveToSideboard": "Move to Sideboard",
      "moveToMaybeboard": "Move to Maybeboard"
    },
    "footer": {
      "description": "The ultimate AI-powered Magic: The Gathering deck building and analysis tool. Your specialized real estate personal shopper for cards, a 100% buyer-focused service.",
      "product": "Product",
      "resources": "Resources",
      "scryfall": "Scryfall",
      "moxfield": "Moxfield",
      "magicOfficial": "Magic: The Gathering Official",
      "legal": "Legal",
      "documentation": "Documentation",
      "api": "API",
      "status": "System Status",
      "privacy": "Privacy",
      "terms": "Terms",
      "cookies": "Cookies",
      "legalDisclaimer": "Wizards of the Coast, Magic: The Gathering, and their logos are trademarks of Wizards of the Coast LLC. © 1993-{year} Wizards of the Coast LLC. Mana Forge is not affiliated with, endorsed, or sponsored by Wizards of the Coast LLC. Card data and imagery are provided by Scryfall; Mana Forge is not affiliated with or endorsed by Scryfall. For more information about Wizards of the Coast, visit",
      "rightsReserved": "All rights reserved.",
      "builtBy": "Built by: "
    },
    "legal": {
      "cookies": {
        "title": "Manage Consent",
        "bannerTextLong": "We use technologies like cookies, both our own and from third parties, to store and/or access device information. Using these technologies will allow us to process data such as browsing behavior or unique IDs on this website. Not consenting or withdrawing consent may adversely affect certain features and functions.",
        "bannerHint": "You can accept the use of Cookies by clicking Accept, deny them by clicking Deny, or configure them in View Preferences. More information in our {policyLink}.",
        "policyLink": "Cookie Policy",
        "accept": "Accept",
        "reject": "Deny",
        "viewPreferences": "View Preferences",
        "savePreferences": "Save Preferences",
        "alwaysActive": "Always Active",
        "recommended": "Recommended",
        "categories": {
          "functional": {
            "title": "Functional",
            "description": "The technical storage or access is strictly necessary for the legitimate purpose of enabling the use of a specific service explicitly requested by the subscriber or user, or for the sole purpose of carrying out the transmission of a communication over an electronic communications network."
          },
          "preferences": {
            "title": "Preferences",
            "description": "The technical storage or access is necessary for the legitimate purpose of storing preferences not requested by the subscriber or user."
          },
          "statistics": {
            "title": "Statistics",
            "description": "The technical storage or access that is used exclusively for anonymous statistical purposes. Without a subpoena, voluntary compliance on the part of your Internet Service Provider, or additional records from a third party, information stored or retrieved for this purpose alone cannot usually be used to identify you."
          },
          "marketing": {
            "title": "Marketing",
            "description": "The technical storage or access is required to create user profiles to send advertising, or to track the user on a website or across several websites for similar marketing purposes."
          }
        }
      },
      "notFoundTitle": "Legal page not found",
      "notFoundDescription": "Sorry, we couldn't find the legal content you're looking for.",
      "backToHome": "Back to home",
      "lastUpdated": "Last updated:",
      "tableOfContents": "Contents"
    },
    "deckViewer": {
      "notFound": "Deck not found",
      "group": "Group",
      "groupType": "By type",
      "groupNone": "No grouping",
      "viewList": "List",
      "viewSpoiler": "Spoiler",
      "sort": "Sort",
      "sortCmc": "By cost",
      "sortAlpha": "Alphabetical",
      "sortAsc": "Ascending",
      "sortDesc": "Descending",
      "summary": "Summary",
      "showPrices": "Show prices",
      "hidePrices": "Hide prices",
      "totalPrice": "Total price",
      "noPrice": "N/A",
      "total": "Total",
      "cardTypes": {
        "Commander": "Commander",
        "Planeswalker": "Planeswalker",
        "Creature": "Creature",
        "Battle": "Battle",
        "Instant": "Instant",
        "Sorcery": "Sorcery",
        "Enchantment": "Enchantment",
        "Artifact": "Artifact",
        "Land": "Land",
        "Other": "Other",
        "All": "All",
        "Unknown": "Other"
      }
    },
    "notFound": {
      "title": "Page not found",
      "description": "The route you're looking for doesn't exist or has been moved.",
      "goHome": "Go home",
      "goBack": "Go back"
    },
    "friends": {
      "title": "Friends",
      "subtitle": "Manage your friends and friend requests",
      "explorerSubtitle": "Discover the best strategies from the community",
      "searchPlaceholder": "Search users by name...",
      "noResults": "No users found",
      "tab": {
        "friends": "My Friends",
        "requests": "Requests"
      },
      "addFriend": "Add",
      "alreadyFriend": "Already friends",
      "pending": "Pending",
      "noFriends": "You have no friends yet. Search for users to add them!",
      "remove": "Remove",
      "received": "Received",
      "sent": "Sent",
      "noReceived": "No pending requests",
      "noSent": "No sent requests",
      "accept": "Accept",
      "reject": "Reject",
      "cancel": "Cancel",
      "requestSent": "Friend request sent",
      "requestAccepted": "You are now friends!",
      "requestRejected": "Request rejected",
      "friendRemoved": "Friend removed",
      "alreadyExists": "A pending request already exists",
      "requestError": "Error processing the request",
      "loadError": "Error loading data",
      "follow": "Follow",
      "unfollow": "Following",
      "followers": "followers",
      "following": "following",
      "followError": "Error updating follow",
      "message": "Message",
      "sendMessage": "Send message"
    },
    "messages": {
      "title": "Messages",
      "noConversation": "Select a conversation",
      "noConversationHint": "Choose a friend from the list to start chatting",
      "noFriendsToMessage": "Add friends to send messages",
      "placeholder": "Write a message...",
      "empty": "No messages yet. Say hi!",
      "sendError": "Error sending message",
      "loadError": "Error loading messages"
    },
    "explorer": {
      "sortLabel": "Sort by",
      "sortRecent": "Most recent",
      "sortPopular": "Most popular",
      "sortNameAZ": "Name A-Z",
      "noDecks": "No decks found",
      "clearFilters": "Clear filters"
    },
    "seo": {
      "defaultTitle": "Mana Forge | Your AI MTG Deck Forge",
      "defaultDescription": "Mana Forge helps you build, analyze, and perfect your Magic: The Gathering decks. The ideal real estate personal shopper for cards, a 100% buyer-focused service.",
      "dashboardTitle": "Home",
      "dashboardDescription": "Explore the latest news, popular formats, and the daily deck generated by AI.",
      "deckBuilderTitle": "Deck Forge",
      "deckBuilderDescription": "Create and analyze your Magic decks. Optimize your mana curve and strategy with advanced AI analysis.",
      "myDecksTitle": "My Decks",
      "myDecksDescription": "Manage your collection of saved decks.",
      "explorerTitle": "Deck Explorer",
      "explorerDescription": "Discover the most powerful decks created by the community of players.",
      "friendsTitle": "Friends",
      "friendsDescription": "Connect with other players and share your creations.",
      "profileTitle": "My Profile",
      "profileDescription": "Configure your preferences to personalize your experience on the platform."
    }
  }
}
